translatevideo/__init__.py
translatevideo/concatsrtfiles.py
translatevideo/genaisubtitles.py
translatevideo/gensubtitles.py
translatevideo/removeduplicatelinessrt.py
translatevideo/scansubtitles.py
translatevideo/utilities.py
translatevideo-0.8.5.dist-info/METADATA
translatevideo-0.8.5.dist-info/WHEEL
translatevideo-0.8.5.dist-info/entry_points.txt
translatevideo-0.8.5.dist-info/top_level.txt
translatevideo-0.8.5.dist-info/RECORD
