Metadata-Version: 2.2
Name: translatevideo
Version: 0.8.5
Summary: Bulk Generate SRT Subtitles From Video Locally No API Needed
Author: codexhound
License: MIT License
Project-URL: Homepage, https://github.com/codexhound/translatevideo
Project-URL: Issues, https://github.com/codexhound/translatevideo/issues
Keywords: translation,subtitles,transcription,srt,plex
Classifier: Programming Language :: Python :: 3
Classifier: License :: OSI Approved :: MIT License
Classifier: Operating System :: OS Independent
Requires-Python: >=3.8
Requires-Dist: pycountry
Requires-Dist: pandas
Requires-Dist: pydub
Requires-Dist: argparse
